setup.py
pyc_viewer/__init__.py
pyc_viewer.egg-info/PKG-INFO
pyc_viewer.egg-info/SOURCES.txt
pyc_viewer.egg-info/dependency_links.txt
pyc_viewer.egg-info/entry_points.txt
pyc_viewer.egg-info/top_level.txt