Metadata-Version: 1.0
Name: pyc-viewer
Version: 0.0.1
Summary: Python bytecode viewer
Home-page: https://github.com/guoxiaoyong/pyc_viewer
Author: Guo Xiaoyong
Author-email: guo.xiaoyong@gmail.com
License: UNKNOWN
Platform: UNKNOWN
